hemlock_crt/__init__.py
hemlock_crt/items.py
hemlock_crt-0.0.2.dist-info/LICENSE
hemlock_crt-0.0.2.dist-info/METADATA
hemlock_crt-0.0.2.dist-info/WHEEL
hemlock_crt-0.0.2.dist-info/top_level.txt
hemlock_crt-0.0.2.dist-info/RECORD
