Metadata-Version: 2.1
Name: hemlock-crt
Version: 0.0.2
Summary: Cognitive Reflection Test for Hemlock projects
Home-page: https://github.com/dsbowen/hemlock-crt
Author: Dillon Bowen
Author-email: dsbowen@example.com
License: UNKNOWN
Platform: UNKNOWN
Classifier: Programming Language :: Python :: 3
Classifier: License :: OSI Approved :: MIT License
Classifier: Operating System :: OS Independent
Requires-Python: >=3.6
